[
  {
    "oid": "24d9d398bb8da468aa6a7b4db755ce9eedf5c20a",
    "statuses": [
      {
        "name": "CI / MacOS",
        "status": "PENDING",
        "url": "https://github.com/apache/tvm/runs/7823916098?check_suite_focus=true"
      },
      {
        "name": "CI / Windows",
        "status": "PENDING",
        "url": "https://github.com/apache/tvm/runs/7823916038?check_suite_focus=true"
      },
      {
        "name": "CI / Android",
        "status": "PENDING",
        "url": "https://github.com/apache/tvm/runs/7823916159?check_suite_focus=true"
      },
      {
        "name": "tvm-ci/branch",
        "status": "PENDING",
        "url": "https://ci.tlcpack.ai/job/tvm/job/main/4054/display/redirect"
      }
    ],
    "messageHeadline": "Add `operator()` to `support::With` (#12418)"
  },
  {
    "oid": "0ac5dd7f645298e0ebf1e3be643842814efdc514",
    "statuses": [
      {
        "name": "CI / MacOS",
        "status": "PENDING",
        "url": "https://github.com/apache/tvm/runs/7823562916?check_suite_focus=true"
      },
      {
        "name": "CI / Windows",
        "status": "PENDING",
        "url": "https://github.com/apache/tvm/runs/7823562837?check_suite_focus=true"
      },
      {
        "name": "CI / Android",
        "status": "PENDING",
        "url": "https://github.com/apache/tvm/runs/7823562806?check_suite_focus=true"
      },
      {
        "name": "tvm-ci/branch",
        "status": "PENDING",
        "url": "https://ci.tlcpack.ai/job/tvm/job/main/4053/display/redirect"
      }
    ],
    "messageHeadline": "[Fix] Fix errors in error checking and reporting (#12423)"
  },
  {
    "oid": "33bf70875513a6bb97a2e038b0b387f9ed0f9d9d",
    "statuses": [
      {
        "name": "CI / MacOS",
        "status": "PENDING",
        "url": "https://github.com/apache/tvm/runs/7823556566?check_suite_focus=true"
      },
      {
        "name": "CI / Windows",
        "status": "PENDING",
        "url": "https://github.com/apache/tvm/runs/7823556586?check_suite_focus=true"
      },
      {
        "name": "CI / Android",
        "status": "PENDING",
        "url": "https://github.com/apache/tvm/runs/7823556534?check_suite_focus=true"
      },
      {
        "name": "tvm-ci/branch",
        "status": "PENDING",
        "url": "https://ci.tlcpack.ai/job/tvm/job/main/4052/display/redirect"
      }
    ],
    "messageHeadline": "[Fix] Fix precision issue in FFI converting `int/float` to `PrimExpr`\u2026"
  },
  {
    "oid": "d8846ec9757fae6b9db7778dccc1dd8f7619ebe2",
    "statuses": [
      {
        "name": "CI / MacOS",
        "status": "SUCCESS",
        "url": "https://github.com/apache/tvm/runs/7823428681?check_suite_focus=true"
      },
      {
        "name": "CI / Windows",
        "status": "SUCCESS",
        "url": "https://github.com/apache/tvm/runs/7823428637?check_suite_focus=true"
      },
      {
        "name": "CI / Android",
        "status": "SUCCESS",
        "url": "https://github.com/apache/tvm/runs/7823428593?check_suite_focus=true"
      },
      {
        "name": "tvm-ci/branch",
        "status": "PENDING",
        "url": "https://ci.tlcpack.ai/job/tvm/job/main/4051/display/redirect"
      }
    ],
    "messageHeadline": "[TOPI][OP]change float multiplication of resize op to integer divisio\u2026"
  },
  {
    "oid": "8dd621e56485fb1926ad2e83c3f17981a9fdaac8",
    "statuses": [
      {
        "name": "CI / MacOS",
        "status": "SUCCESS",
        "url": "https://github.com/apache/tvm/runs/7823358064?check_suite_focus=true"
      },
      {
        "name": "CI / Windows",
        "status": "SUCCESS",
        "url": "https://github.com/apache/tvm/runs/7823358085?check_suite_focus=true"
      },
      {
        "name": "CI / Android",
        "status": "FAILURE",
        "url": "https://github.com/apache/tvm/runs/7823358114?check_suite_focus=true"
      },
      {
        "name": "tvm-ci/branch",
        "status": "PENDING",
        "url": "https://ci.tlcpack.ai/job/tvm/job/main/4050/display/redirect"
      }
    ],
    "messageHeadline": "[TIR] Expose ScriptComplete in header (#12419)"
  },
  {
    "oid": "d33a332283e7349088ba7aa57e56534518bb088b",
    "statuses": [
      {
        "name": "CI / MacOS",
        "status": "SUCCESS",
        "url": "https://github.com/apache/tvm/runs/7821585058?check_suite_focus=true"
      },
      {
        "name": "CI / Windows",
        "status": "SUCCESS",
        "url": "https://github.com/apache/tvm/runs/7821585090?check_suite_focus=true"
      },
      {
        "name": "CI / Android",
        "status": "SUCCESS",
        "url": "https://github.com/apache/tvm/runs/7821585018?check_suite_focus=true"
      },
      {
        "name": "tvm-ci/branch",
        "status": "SUCCESS",
        "url": "https://ci.tlcpack.ai/job/tvm/job/main/4049/display/redirect"
      }
    ],
    "messageHeadline": "[TVMScript] Printer VarTable (#12336)"
  },
  {
    "oid": "036aa722aefd7126c17063cddb260b9347f17598",
    "statuses": [
      {
        "name": "CI / MacOS",
        "status": "SUCCESS",
        "url": "https://github.com/apache/tvm/runs/7817952822?check_suite_focus=true"
      },
      {
        "name": "CI / Windows",
        "status": "SUCCESS",
        "url": "https://github.com/apache/tvm/runs/7817952912?check_suite_focus=true"
      },
      {
        "name": "CI / Android",
        "status": "SUCCESS",
        "url": "https://github.com/apache/tvm/runs/7817952721?check_suite_focus=true"
      },
      {
        "name": "tvm-ci/branch",
        "status": "SUCCESS",
        "url": "https://ci.tlcpack.ai/job/tvm/job/main/4048/display/redirect"
      }
    ],
    "messageHeadline": "[TIR] Add pass ManifestSharedMemoryLocalStage (#12355)"
  },
  {
    "oid": "96cac7501dbce42af6c5bb6f75b51a4b70c4077a",
    "statuses": [
      {
        "name": "CI / MacOS",
        "status": "SUCCESS",
        "url": "https://github.com/apache/tvm/runs/7817948971?check_suite_focus=true"
      },
      {
        "name": "CI / Windows",
        "status": "SUCCESS",
        "url": "https://github.com/apache/tvm/runs/7817948898?check_suite_focus=true"
      },
      {
        "name": "CI / Android",
        "status": "SUCCESS",
        "url": "https://github.com/apache/tvm/runs/7817948840?check_suite_focus=true"
      },
      {
        "name": "tvm-ci/branch",
        "status": "SUCCESS",
        "url": "https://ci.tlcpack.ai/job/tvm/job/main/4047/display/redirect"
      }
    ],
    "messageHeadline": "[MetaSchedule] Filter vector_load_lens based on buffer dtype (#12408)"
  },
  {
    "oid": "1737308397e0f105c387d9ee6c466584aded1d7d",
    "statuses": [
      {
        "name": "CI / MacOS",
        "status": "SUCCESS",
        "url": "https://github.com/apache/tvm/runs/7814894943?check_suite_focus=true"
      },
      {
        "name": "CI / Windows",
        "status": "SUCCESS",
        "url": "https://github.com/apache/tvm/runs/7814894753?check_suite_focus=true"
      },
      {
        "name": "CI / Android",
        "status": "SUCCESS",
        "url": "https://github.com/apache/tvm/runs/7814894623?check_suite_focus=true"
      },
      {
        "name": "tvm-ci/branch",
        "status": "ERROR",
        "url": "https://ci.tlcpack.ai/job/tvm/job/main/4046/display/redirect"
      }
    ],
    "messageHeadline": "[WIP][Pylint] Making frontend tests pylint compliant (#12028)"
  },
  {
    "oid": "478b672f2b7bb37f529fa6477b3c4ac353217b7a",
    "statuses": [
      {
        "name": "tvm-ci/branch",
        "status": "SUCCESS",
        "url": "https://ci.tlcpack.ai/job/tvm/job/main/4045/display/redirect"
      }
    ],
    "messageHeadline": "[skip ci] Revert \"[ci] Default to n=2 for test parallelism (#12376)\" \u2026"
  },
  {
    "oid": "57a02f7e26f1f8e0f53081851a17cf501367036f",
    "statuses": [
      {
        "name": "CI / MacOS",
        "status": "SUCCESS",
        "url": "https://github.com/apache/tvm/runs/7813153069?check_suite_focus=true"
      },
      {
        "name": "CI / Windows",
        "status": "SUCCESS",
        "url": "https://github.com/apache/tvm/runs/7813153225?check_suite_focus=true"
      },
      {
        "name": "CI / Android",
        "status": "SUCCESS",
        "url": "https://github.com/apache/tvm/runs/7813152877?check_suite_focus=true"
      },
      {
        "name": "tvm-ci/branch",
        "status": "SUCCESS",
        "url": "https://ci.tlcpack.ai/job/tvm/job/main/4044/display/redirect"
      }
    ],
    "messageHeadline": "Update hexagon max_concurrency to be at most equal to the number of H\u2026"
  },
  {
    "oid": "3eb673478bc444daf24ee8d6308a42a71c81b74f",
    "statuses": [
      {
        "name": "CI / MacOS",
        "status": "SUCCESS",
        "url": "https://github.com/apache/tvm/runs/7813141992?check_suite_focus=true"
      },
      {
        "name": "CI / Windows",
        "status": "SUCCESS",
        "url": "https://github.com/apache/tvm/runs/7813142271?check_suite_focus=true"
      },
      {
        "name": "CI / Android",
        "status": "SUCCESS",
        "url": "https://github.com/apache/tvm/runs/7813142154?check_suite_focus=true"
      },
      {
        "name": "tvm-ci/branch",
        "status": "ERROR",
        "url": "https://ci.tlcpack.ai/job/tvm/job/main/4043/display/redirect"
      }
    ],
    "messageHeadline": "[LowerVTCMAlloc] Move LowerVtcmAlloc to after StorageRewrite (#12364)"
  },
  {
    "oid": "779a7ada4f263f4d1faf0eec651fdab5cf9eaaa4",
    "statuses": [
      {
        "name": "CI / MacOS",
        "status": "SUCCESS",
        "url": "https://github.com/apache/tvm/runs/7811553430?check_suite_focus=true"
      },
      {
        "name": "CI / Windows",
        "status": "SUCCESS",
        "url": "https://github.com/apache/tvm/runs/7811553539?check_suite_focus=true"
      },
      {
        "name": "CI / Android",
        "status": "SUCCESS",
        "url": "https://github.com/apache/tvm/runs/7811553304?check_suite_focus=true"
      },
      {
        "name": "tvm-ci/branch",
        "status": "SUCCESS",
        "url": "https://ci.tlcpack.ai/job/tvm/job/main/4042/display/redirect"
      }
    ],
    "messageHeadline": "Add sort_by_time flag to debug_executor.run method (#12402)"
  },
  {
    "oid": "db1ed779f89206359954c0a187c5de7bb608debc",
    "statuses": [
      {
        "name": "CI / MacOS",
        "status": "SUCCESS",
        "url": "https://github.com/apache/tvm/runs/7811278156?check_suite_focus=true"
      },
      {
        "name": "CI / Windows",
        "status": "SUCCESS",
        "url": "https://github.com/apache/tvm/runs/7811278254?check_suite_focus=true"
      },
      {
        "name": "CI / Android",
        "status": "SUCCESS",
        "url": "https://github.com/apache/tvm/runs/7811278028?check_suite_focus=true"
      },
      {
        "name": "tvm-ci/branch",
        "status": "SUCCESS",
        "url": "https://ci.tlcpack.ai/job/tvm/job/main/4041/display/redirect"
      }
    ],
    "messageHeadline": "[docs] Update minimum compiler requirements for building from source \u2026"
  },
  {
    "oid": "c3c7c4ccc3e3ebb7cc4dbb55e8dde579ac52c949",
    "statuses": [
      {
        "name": "CI / MacOS",
        "status": "SUCCESS",
        "url": "https://github.com/apache/tvm/runs/7810015350?check_suite_focus=true"
      },
      {
        "name": "CI / Windows",
        "status": "SUCCESS",
        "url": "https://github.com/apache/tvm/runs/7810015172?check_suite_focus=true"
      },
      {
        "name": "CI / Android",
        "status": "SUCCESS",
        "url": "https://github.com/apache/tvm/runs/7810015467?check_suite_focus=true"
      },
      {
        "name": "tvm-ci/branch",
        "status": "ERROR",
        "url": "https://ci.tlcpack.ai/job/tvm/job/main/4040/display/redirect"
      }
    ],
    "messageHeadline": "[Profiler] Fix graph_executor_debug hang (#12382)"
  }
]