[
  {
    "oid": "0bb390b272981887d976b299a29f757864af0908",
    "statuses": [
      {
        "name": "CI / MacOS",
        "status": "SUCCESS",
        "url": "https://github.com/apache/tvm/actions/runs/5461096962/jobs/9938719022"
      },
      {
        "name": "CI / Windows",
        "status": "SUCCESS",
        "url": "https://github.com/apache/tvm/actions/runs/5461096962/jobs/9938718933"
      },
      {
        "name": "CI / Linux-Static-Runtime",
        "status": "SUCCESS",
        "url": "https://github.com/apache/tvm/actions/runs/5461096962/jobs/9938719109"
      },
      {
        "name": "CI / Android",
        "status": "SUCCESS",
        "url": "https://github.com/apache/tvm/actions/runs/5461096962/jobs/9938718833"
      },
      {
        "name": "cortexm/branch",
        "status": "PENDING",
        "url": "https://ci.tlcpack.ai/job/tvm-cortexm/job/main/858/display/redirect"
      },
      {
        "name": "cpu/branch",
        "status": "PENDING",
        "url": "https://ci.tlcpack.ai/job/tvm-cpu/job/main/858/display/redirect"
      },
      {
        "name": "cross-isa-minimal/branch",
        "status": "PENDING",
        "url": "https://ci.tlcpack.ai/job/tvm-minimal-cross-isa/job/main/686/display/redirect"
      },
      {
        "name": "gpu/branch",
        "status": "PENDING",
        "url": "https://ci.tlcpack.ai/job/tvm-gpu/job/main/865/display/redirect"
      },
      {
        "name": "hexagon/branch",
        "status": "PENDING",
        "url": "https://ci.tlcpack.ai/job/tvm-hexagon/job/main/851/display/redirect"
      },
      {
        "name": "minimal/branch",
        "status": "PENDING",
        "url": "https://ci.tlcpack.ai/job/tvm-minimal/job/main/847/display/redirect"
      },
      {
        "name": "arm/branch",
        "status": "SUCCESS",
        "url": "https://ci.tlcpack.ai/job/tvm-arm/job/main/1156/display/redirect"
      },
      {
        "name": "docker/branch",
        "status": "SUCCESS",
        "url": "https://ci.tlcpack.ai/job/tvm-docker/job/main/857/display/redirect"
      },
      {
        "name": "i386/branch",
        "status": "SUCCESS",
        "url": "https://ci.tlcpack.ai/job/tvm-i386/job/main/852/display/redirect"
      },
      {
        "name": "lint/branch",
        "status": "SUCCESS",
        "url": "https://ci.tlcpack.ai/job/tvm-lint/job/main/849/display/redirect"
      },
      {
        "name": "riscv/branch",
        "status": "SUCCESS",
        "url": "https://ci.tlcpack.ai/job/tvm-riscv/job/main/847/display/redirect"
      },
      {
        "name": "wasm/branch",
        "status": "SUCCESS",
        "url": "https://ci.tlcpack.ai/job/tvm-wasm/job/main/844/display/redirect"
      }
    ],
    "messageHeadline": "[UnitTest][NVPTX] Avoid cascading failures from CUDA postproc (#15136)"
  },
  {
    "oid": "c928852d59282e39cd5fc162785a4fdf56c5aa1b",
    "statuses": [
      {
        "name": "CI / MacOS",
        "status": "SUCCESS",
        "url": "https://github.com/apache/tvm/actions/runs/5461091933/jobs/9938708565"
      },
      {
        "name": "CI / Windows",
        "status": "SUCCESS",
        "url": "https://github.com/apache/tvm/actions/runs/5461091933/jobs/9938708477"
      },
      {
        "name": "CI / Linux-Static-Runtime",
        "status": "SUCCESS",
        "url": "https://github.com/apache/tvm/actions/runs/5461091933/jobs/9938708660"
      },
      {
        "name": "CI / Android",
        "status": "SUCCESS",
        "url": "https://github.com/apache/tvm/actions/runs/5461091933/jobs/9938708768"
      },
      {
        "name": "cpu/branch",
        "status": "PENDING",
        "url": "https://ci.tlcpack.ai/job/tvm-cpu/job/main/857/display/redirect"
      },
      {
        "name": "cross-isa-minimal/branch",
        "status": "PENDING",
        "url": "https://ci.tlcpack.ai/job/tvm-minimal-cross-isa/job/main/685/display/redirect"
      },
      {
        "name": "gpu/branch",
        "status": "PENDING",
        "url": "https://ci.tlcpack.ai/job/tvm-gpu/job/main/864/display/redirect"
      },
      {
        "name": "hexagon/branch",
        "status": "PENDING",
        "url": "https://ci.tlcpack.ai/job/tvm-hexagon/job/main/850/display/redirect"
      },
      {
        "name": "minimal/branch",
        "status": "PENDING",
        "url": "https://ci.tlcpack.ai/job/tvm-minimal/job/main/846/display/redirect"
      },
      {
        "name": "arm/branch",
        "status": "SUCCESS",
        "url": "https://ci.tlcpack.ai/job/tvm-arm/job/main/1155/display/redirect"
      },
      {
        "name": "cortexm/branch",
        "status": "SUCCESS",
        "url": "https://ci.tlcpack.ai/job/tvm-cortexm/job/main/857/display/redirect"
      },
      {
        "name": "docker/branch",
        "status": "SUCCESS",
        "url": "https://ci.tlcpack.ai/job/tvm-docker/job/main/856/display/redirect"
      },
      {
        "name": "i386/branch",
        "status": "SUCCESS",
        "url": "https://ci.tlcpack.ai/job/tvm-i386/job/main/851/display/redirect"
      },
      {
        "name": "lint/branch",
        "status": "SUCCESS",
        "url": "https://ci.tlcpack.ai/job/tvm-lint/job/main/848/display/redirect"
      },
      {
        "name": "riscv/branch",
        "status": "SUCCESS",
        "url": "https://ci.tlcpack.ai/job/tvm-riscv/job/main/846/display/redirect"
      },
      {
        "name": "wasm/branch",
        "status": "SUCCESS",
        "url": "https://ci.tlcpack.ai/job/tvm-wasm/job/main/843/display/redirect"
      }
    ],
    "messageHeadline": "[#15157][Rust][Doc] Re-enable the Rust documentation build (#15213)"
  },
  {
    "oid": "23fb56852122919a2ea896000d87be163e2b1bb5",
    "statuses": [
      {
        "name": "CI / MacOS",
        "status": "SUCCESS",
        "url": "https://github.com/apache/tvm/actions/runs/5460863744/jobs/9938244762"
      },
      {
        "name": "CI / Windows",
        "status": "SUCCESS",
        "url": "https://github.com/apache/tvm/actions/runs/5460863744/jobs/9938244838"
      },
      {
        "name": "CI / Linux-Static-Runtime",
        "status": "SUCCESS",
        "url": "https://github.com/apache/tvm/actions/runs/5460863744/jobs/9938244697"
      },
      {
        "name": "CI / Android",
        "status": "SUCCESS",
        "url": "https://github.com/apache/tvm/actions/runs/5460863744/jobs/9938244912"
      },
      {
        "name": "gpu/branch",
        "status": "PENDING",
        "url": "https://ci.tlcpack.ai/job/tvm-gpu/job/main/863/display/redirect"
      },
      {
        "name": "arm/branch",
        "status": "SUCCESS",
        "url": "https://ci.tlcpack.ai/job/tvm-arm/job/main/1154/display/redirect"
      },
      {
        "name": "cortexm/branch",
        "status": "SUCCESS",
        "url": "https://ci.tlcpack.ai/job/tvm-cortexm/job/main/856/display/redirect"
      },
      {
        "name": "cpu/branch",
        "status": "SUCCESS",
        "url": "https://ci.tlcpack.ai/job/tvm-cpu/job/main/856/display/redirect"
      },
      {
        "name": "cross-isa-minimal/branch",
        "status": "SUCCESS",
        "url": "https://ci.tlcpack.ai/job/tvm-minimal-cross-isa/job/main/684/display/redirect"
      },
      {
        "name": "docker/branch",
        "status": "SUCCESS",
        "url": "https://ci.tlcpack.ai/job/tvm-docker/job/main/855/display/redirect"
      },
      {
        "name": "hexagon/branch",
        "status": "SUCCESS",
        "url": "https://ci.tlcpack.ai/job/tvm-hexagon/job/main/849/display/redirect"
      },
      {
        "name": "i386/branch",
        "status": "SUCCESS",
        "url": "https://ci.tlcpack.ai/job/tvm-i386/job/main/850/display/redirect"
      },
      {
        "name": "lint/branch",
        "status": "SUCCESS",
        "url": "https://ci.tlcpack.ai/job/tvm-lint/job/main/847/display/redirect"
      },
      {
        "name": "minimal/branch",
        "status": "SUCCESS",
        "url": "https://ci.tlcpack.ai/job/tvm-minimal/job/main/845/display/redirect"
      },
      {
        "name": "riscv/branch",
        "status": "SUCCESS",
        "url": "https://ci.tlcpack.ai/job/tvm-riscv/job/main/845/display/redirect"
      },
      {
        "name": "wasm/branch",
        "status": "SUCCESS",
        "url": "https://ci.tlcpack.ai/job/tvm-wasm/job/main/842/display/redirect"
      }
    ],
    "messageHeadline": "[CMAKE] Add Vulkan header for Android (#15229)"
  },
  {
    "oid": "8f9f605dd599a623cf56159fe24bd8fd08489c2b",
    "statuses": [
      {
        "name": "CI / MacOS",
        "status": "SUCCESS",
        "url": "https://github.com/apache/tvm/actions/runs/5459633385/jobs/9935829107"
      },
      {
        "name": "CI / Windows",
        "status": "SUCCESS",
        "url": "https://github.com/apache/tvm/actions/runs/5459633385/jobs/9935829190"
      },
      {
        "name": "CI / Linux-Static-Runtime",
        "status": "SUCCESS",
        "url": "https://github.com/apache/tvm/actions/runs/5459633385/jobs/9935829247"
      },
      {
        "name": "CI / Android",
        "status": "SUCCESS",
        "url": "https://github.com/apache/tvm/actions/runs/5459633385/jobs/9935828980"
      },
      {
        "name": "gpu/branch",
        "status": "PENDING",
        "url": "https://ci.tlcpack.ai/job/tvm-gpu/job/nightly/194/display/redirect"
      },
      {
        "name": "arm/branch",
        "status": "SUCCESS",
        "url": "https://ci.tlcpack.ai/job/tvm-arm/job/nightly/201/display/redirect"
      },
      {
        "name": "cortexm/branch",
        "status": "SUCCESS",
        "url": "https://ci.tlcpack.ai/job/tvm-cortexm/job/nightly/193/display/redirect"
      },
      {
        "name": "cpu/branch",
        "status": "SUCCESS",
        "url": "https://ci.tlcpack.ai/job/tvm-cpu/job/nightly/193/display/redirect"
      },
      {
        "name": "cross-isa-minimal/branch",
        "status": "SUCCESS",
        "url": "https://ci.tlcpack.ai/job/tvm-minimal-cross-isa/job/nightly/157/display/redirect"
      },
      {
        "name": "docker/branch",
        "status": "SUCCESS",
        "url": "https://ci.tlcpack.ai/job/tvm-docker/job/nightly/193/display/redirect"
      },
      {
        "name": "hexagon/branch",
        "status": "SUCCESS",
        "url": "https://ci.tlcpack.ai/job/tvm-hexagon/job/nightly/194/display/redirect"
      },
      {
        "name": "i386/branch",
        "status": "SUCCESS",
        "url": "https://ci.tlcpack.ai/job/tvm-i386/job/nightly/193/display/redirect"
      },
      {
        "name": "lint/branch",
        "status": "SUCCESS",
        "url": "https://ci.tlcpack.ai/job/tvm-lint/job/nightly/193/display/redirect"
      },
      {
        "name": "minimal/branch",
        "status": "SUCCESS",
        "url": "https://ci.tlcpack.ai/job/tvm-minimal/job/nightly/193/display/redirect"
      },
      {
        "name": "riscv/branch",
        "status": "SUCCESS",
        "url": "https://ci.tlcpack.ai/job/tvm-riscv/job/nightly/193/display/redirect"
      },
      {
        "name": "wasm/branch",
        "status": "SUCCESS",
        "url": "https://ci.tlcpack.ai/job/tvm-wasm/job/nightly/193/display/redirect"
      }
    ],
    "messageHeadline": "[ARITH] Enhance buffer shape bound deduction to include offset (#15228)"
  },
  {
    "oid": "516c56b46aa60b7e25c526470ca3dbcb80de0272",
    "statuses": [
      {
        "name": "CI / MacOS",
        "status": "SUCCESS",
        "url": "https://github.com/apache/tvm/actions/runs/5454701190/jobs/9925172987"
      },
      {
        "name": "CI / Windows",
        "status": "SUCCESS",
        "url": "https://github.com/apache/tvm/actions/runs/5454701190/jobs/9925172438"
      },
      {
        "name": "CI / Linux-Static-Runtime",
        "status": "SUCCESS",
        "url": "https://github.com/apache/tvm/actions/runs/5454701190/jobs/9925172630"
      },
      {
        "name": "CI / Android",
        "status": "SUCCESS",
        "url": "https://github.com/apache/tvm/actions/runs/5454701190/jobs/9925172829"
      },
      {
        "name": "arm/branch",
        "status": "SUCCESS",
        "url": "https://ci.tlcpack.ai/job/tvm-arm/job/main/1152/display/redirect"
      },
      {
        "name": "cortexm/branch",
        "status": "SUCCESS",
        "url": "https://ci.tlcpack.ai/job/tvm-cortexm/job/main/854/display/redirect"
      },
      {
        "name": "cpu/branch",
        "status": "SUCCESS",
        "url": "https://ci.tlcpack.ai/job/tvm-cpu/job/main/854/display/redirect"
      },
      {
        "name": "cross-isa-minimal/branch",
        "status": "SUCCESS",
        "url": "https://ci.tlcpack.ai/job/tvm-minimal-cross-isa/job/main/682/display/redirect"
      },
      {
        "name": "docker/branch",
        "status": "SUCCESS",
        "url": "https://ci.tlcpack.ai/job/tvm-docker/job/main/853/display/redirect"
      },
      {
        "name": "gpu/branch",
        "status": "SUCCESS",
        "url": "https://ci.tlcpack.ai/job/tvm-gpu/job/main/861/display/redirect"
      },
      {
        "name": "hexagon/branch",
        "status": "SUCCESS",
        "url": "https://ci.tlcpack.ai/job/tvm-hexagon/job/main/847/display/redirect"
      },
      {
        "name": "i386/branch",
        "status": "SUCCESS",
        "url": "https://ci.tlcpack.ai/job/tvm-i386/job/main/848/display/redirect"
      },
      {
        "name": "lint/branch",
        "status": "SUCCESS",
        "url": "https://ci.tlcpack.ai/job/tvm-lint/job/main/845/display/redirect"
      },
      {
        "name": "minimal/branch",
        "status": "SUCCESS",
        "url": "https://ci.tlcpack.ai/job/tvm-minimal/job/main/843/display/redirect"
      },
      {
        "name": "riscv/branch",
        "status": "SUCCESS",
        "url": "https://ci.tlcpack.ai/job/tvm-riscv/job/main/842/display/redirect"
      },
      {
        "name": "wasm/branch",
        "status": "SUCCESS",
        "url": "https://ci.tlcpack.ai/job/tvm-wasm/job/main/840/display/redirect"
      }
    ],
    "messageHeadline": "[Web] Increase default EMCC compilation total memory size (#15218)"
  },
  {
    "oid": "1d4829e4309918f193c5cf9a87378f49c8f72acd",
    "statuses": [
      {
        "name": "CI / MacOS",
        "status": "SUCCESS",
        "url": "https://github.com/apache/tvm/actions/runs/5454698494/jobs/9925165296"
      },
      {
        "name": "CI / Windows",
        "status": "SUCCESS",
        "url": "https://github.com/apache/tvm/actions/runs/5454698494/jobs/9925165503"
      },
      {
        "name": "CI / Linux-Static-Runtime",
        "status": "SUCCESS",
        "url": "https://github.com/apache/tvm/actions/runs/5454698494/jobs/9925165702"
      },
      {
        "name": "CI / Android",
        "status": "SUCCESS",
        "url": "https://github.com/apache/tvm/actions/runs/5454698494/jobs/9925165917"
      },
      {
        "name": "arm/branch",
        "status": "SUCCESS",
        "url": "https://ci.tlcpack.ai/job/tvm-arm/job/main/1150/display/redirect"
      },
      {
        "name": "cortexm/branch",
        "status": "SUCCESS",
        "url": "https://ci.tlcpack.ai/job/tvm-cortexm/job/main/853/display/redirect"
      },
      {
        "name": "cpu/branch",
        "status": "SUCCESS",
        "url": "https://ci.tlcpack.ai/job/tvm-cpu/job/main/853/display/redirect"
      },
      {
        "name": "docker/branch",
        "status": "SUCCESS",
        "url": "https://ci.tlcpack.ai/job/tvm-docker/job/main/852/display/redirect"
      },
      {
        "name": "gpu/branch",
        "status": "SUCCESS",
        "url": "https://ci.tlcpack.ai/job/tvm-gpu/job/main/860/display/redirect"
      },
      {
        "name": "hexagon/branch",
        "status": "SUCCESS",
        "url": "https://ci.tlcpack.ai/job/tvm-hexagon/job/main/846/display/redirect"
      },
      {
        "name": "i386/branch",
        "status": "SUCCESS",
        "url": "https://ci.tlcpack.ai/job/tvm-i386/job/main/847/display/redirect"
      },
      {
        "name": "lint/branch",
        "status": "SUCCESS",
        "url": "https://ci.tlcpack.ai/job/tvm-lint/job/main/844/display/redirect"
      }
    ],
    "messageHeadline": "[Android] ndk static build (#15215)"
  },
  {
    "oid": "5dc25afc873fd2c1cecabbf87515f29d459986e2",
    "statuses": [
      {
        "name": "CI / MacOS",
        "status": "SUCCESS",
        "url": "https://github.com/apache/tvm/actions/runs/5452565922/jobs/9920243372"
      },
      {
        "name": "CI / Windows",
        "status": "SUCCESS",
        "url": "https://github.com/apache/tvm/actions/runs/5452565922/jobs/9920243549"
      },
      {
        "name": "CI / Linux-Static-Runtime",
        "status": "SUCCESS",
        "url": "https://github.com/apache/tvm/actions/runs/5452565922/jobs/9920243714"
      },
      {
        "name": "CI / Android",
        "status": "SUCCESS",
        "url": "https://github.com/apache/tvm/actions/runs/5452565922/jobs/9920243191"
      },
      {
        "name": "arm/branch",
        "status": "SUCCESS",
        "url": "https://ci.tlcpack.ai/job/tvm-arm/job/main/1149/display/redirect"
      },
      {
        "name": "cortexm/branch",
        "status": "SUCCESS",
        "url": "https://ci.tlcpack.ai/job/tvm-cortexm/job/main/852/display/redirect"
      },
      {
        "name": "cpu/branch",
        "status": "SUCCESS",
        "url": "https://ci.tlcpack.ai/job/tvm-cpu/job/main/852/display/redirect"
      },
      {
        "name": "cross-isa-minimal/branch",
        "status": "SUCCESS",
        "url": "https://ci.tlcpack.ai/job/tvm-minimal-cross-isa/job/main/680/display/redirect"
      },
      {
        "name": "docker/branch",
        "status": "SUCCESS",
        "url": "https://ci.tlcpack.ai/job/tvm-docker/job/main/851/display/redirect"
      },
      {
        "name": "gpu/branch",
        "status": "SUCCESS",
        "url": "https://ci.tlcpack.ai/job/tvm-gpu/job/main/859/display/redirect"
      },
      {
        "name": "hexagon/branch",
        "status": "SUCCESS",
        "url": "https://ci.tlcpack.ai/job/tvm-hexagon/job/main/845/display/redirect"
      },
      {
        "name": "i386/branch",
        "status": "SUCCESS",
        "url": "https://ci.tlcpack.ai/job/tvm-i386/job/main/846/display/redirect"
      },
      {
        "name": "lint/branch",
        "status": "SUCCESS",
        "url": "https://ci.tlcpack.ai/job/tvm-lint/job/main/843/display/redirect"
      },
      {
        "name": "minimal/branch",
        "status": "SUCCESS",
        "url": "https://ci.tlcpack.ai/job/tvm-minimal/job/main/841/display/redirect"
      },
      {
        "name": "riscv/branch",
        "status": "SUCCESS",
        "url": "https://ci.tlcpack.ai/job/tvm-riscv/job/main/841/display/redirect"
      },
      {
        "name": "wasm/branch",
        "status": "SUCCESS",
        "url": "https://ci.tlcpack.ai/job/tvm-wasm/job/main/838/display/redirect"
      }
    ],
    "messageHeadline": "[microNPU][ETHOSU] Add Vela's logic to select configuration block (#1\u2026"
  },
  {
    "oid": "a60b815fe5f97806cbedad79712fb6e618425afe",
    "statuses": [
      {
        "name": "CI / MacOS",
        "status": "SUCCESS",
        "url": "https://github.com/apache/tvm/actions/runs/5447605592/jobs/9909796449"
      },
      {
        "name": "CI / Windows",
        "status": "SUCCESS",
        "url": "https://github.com/apache/tvm/actions/runs/5447605592/jobs/9909796520"
      },
      {
        "name": "CI / Linux-Static-Runtime",
        "status": "SUCCESS",
        "url": "https://github.com/apache/tvm/actions/runs/5447605592/jobs/9909796346"
      },
      {
        "name": "CI / Android",
        "status": "SUCCESS",
        "url": "https://github.com/apache/tvm/actions/runs/5447605592/jobs/9909796270"
      },
      {
        "name": "arm/branch",
        "status": "SUCCESS",
        "url": "https://ci.tlcpack.ai/job/tvm-arm/job/nightly/200/display/redirect"
      },
      {
        "name": "cortexm/branch",
        "status": "SUCCESS",
        "url": "https://ci.tlcpack.ai/job/tvm-cortexm/job/nightly/192/display/redirect"
      },
      {
        "name": "cpu/branch",
        "status": "SUCCESS",
        "url": "https://ci.tlcpack.ai/job/tvm-cpu/job/nightly/192/display/redirect"
      },
      {
        "name": "cross-isa-minimal/branch",
        "status": "SUCCESS",
        "url": "https://ci.tlcpack.ai/job/tvm-minimal-cross-isa/job/nightly/156/display/redirect"
      },
      {
        "name": "docker/branch",
        "status": "SUCCESS",
        "url": "https://ci.tlcpack.ai/job/tvm-docker/job/nightly/192/display/redirect"
      },
      {
        "name": "gpu/branch",
        "status": "SUCCESS",
        "url": "https://ci.tlcpack.ai/job/tvm-gpu/job/nightly/193/display/redirect"
      },
      {
        "name": "hexagon/branch",
        "status": "SUCCESS",
        "url": "https://ci.tlcpack.ai/job/tvm-hexagon/job/nightly/193/display/redirect"
      },
      {
        "name": "i386/branch",
        "status": "SUCCESS",
        "url": "https://ci.tlcpack.ai/job/tvm-i386/job/nightly/192/display/redirect"
      },
      {
        "name": "lint/branch",
        "status": "SUCCESS",
        "url": "https://ci.tlcpack.ai/job/tvm-lint/job/nightly/192/display/redirect"
      },
      {
        "name": "minimal/branch",
        "status": "SUCCESS",
        "url": "https://ci.tlcpack.ai/job/tvm-minimal/job/nightly/192/display/redirect"
      },
      {
        "name": "riscv/branch",
        "status": "SUCCESS",
        "url": "https://ci.tlcpack.ai/job/tvm-riscv/job/nightly/192/display/redirect"
      },
      {
        "name": "wasm/branch",
        "status": "SUCCESS",
        "url": "https://ci.tlcpack.ai/job/tvm-wasm/job/nightly/192/display/redirect"
      }
    ],
    "messageHeadline": "[TIR] Support cross-threaad reduction lowering with thread-broadcasti\u2026"
  },
  {
    "oid": "b160cb1a104d8aaa2efb2afd98e125d276c8e597",
    "statuses": [
      {
        "name": "CI / MacOS",
        "status": "SUCCESS",
        "url": "https://github.com/apache/tvm/actions/runs/5446786387/jobs/9908004572"
      },
      {
        "name": "CI / Windows",
        "status": "SUCCESS",
        "url": "https://github.com/apache/tvm/actions/runs/5446786387/jobs/9908004021"
      },
      {
        "name": "CI / Linux-Static-Runtime",
        "status": "SUCCESS",
        "url": "https://github.com/apache/tvm/actions/runs/5446786387/jobs/9908004222"
      },
      {
        "name": "CI / Android",
        "status": "SUCCESS",
        "url": "https://github.com/apache/tvm/actions/runs/5446786387/jobs/9908004414"
      },
      {
        "name": "arm/branch",
        "status": "SUCCESS",
        "url": "https://ci.tlcpack.ai/job/tvm-arm/job/main/1147/display/redirect"
      },
      {
        "name": "cortexm/branch",
        "status": "SUCCESS",
        "url": "https://ci.tlcpack.ai/job/tvm-cortexm/job/main/850/display/redirect"
      },
      {
        "name": "cpu/branch",
        "status": "SUCCESS",
        "url": "https://ci.tlcpack.ai/job/tvm-cpu/job/main/850/display/redirect"
      },
      {
        "name": "cross-isa-minimal/branch",
        "status": "SUCCESS",
        "url": "https://ci.tlcpack.ai/job/tvm-minimal-cross-isa/job/main/678/display/redirect"
      },
      {
        "name": "docker/branch",
        "status": "SUCCESS",
        "url": "https://ci.tlcpack.ai/job/tvm-docker/job/main/849/display/redirect"
      },
      {
        "name": "gpu/branch",
        "status": "SUCCESS",
        "url": "https://ci.tlcpack.ai/job/tvm-gpu/job/main/857/display/redirect"
      },
      {
        "name": "hexagon/branch",
        "status": "SUCCESS",
        "url": "https://ci.tlcpack.ai/job/tvm-hexagon/job/main/843/display/redirect"
      },
      {
        "name": "i386/branch",
        "status": "SUCCESS",
        "url": "https://ci.tlcpack.ai/job/tvm-i386/job/main/844/display/redirect"
      },
      {
        "name": "lint/branch",
        "status": "SUCCESS",
        "url": "https://ci.tlcpack.ai/job/tvm-lint/job/main/841/display/redirect"
      },
      {
        "name": "minimal/branch",
        "status": "SUCCESS",
        "url": "https://ci.tlcpack.ai/job/tvm-minimal/job/main/839/display/redirect"
      },
      {
        "name": "riscv/branch",
        "status": "SUCCESS",
        "url": "https://ci.tlcpack.ai/job/tvm-riscv/job/main/839/display/redirect"
      },
      {
        "name": "wasm/branch",
        "status": "SUCCESS",
        "url": "https://ci.tlcpack.ai/job/tvm-wasm/job/main/836/display/redirect"
      }
    ],
    "messageHeadline": "Update version to 0.14.dev0 on main branch (#15208)"
  },
  {
    "oid": "03ef29e8ad9c3073881422db3f4f935a9538370d",
    "statuses": [
      {
        "name": "CI / MacOS",
        "status": "SUCCESS",
        "url": "https://github.com/apache/tvm/actions/runs/5446027784/jobs/9906158922"
      },
      {
        "name": "CI / Windows",
        "status": "SUCCESS",
        "url": "https://github.com/apache/tvm/actions/runs/5446027784/jobs/9906158560"
      },
      {
        "name": "CI / Linux-Static-Runtime",
        "status": "SUCCESS",
        "url": "https://github.com/apache/tvm/actions/runs/5446027784/jobs/9906159142"
      },
      {
        "name": "CI / Android",
        "status": "SUCCESS",
        "url": "https://github.com/apache/tvm/actions/runs/5446027784/jobs/9906158748"
      },
      {
        "name": "arm/branch",
        "status": "SUCCESS",
        "url": "https://ci.tlcpack.ai/job/tvm-arm/job/main/1146/display/redirect"
      },
      {
        "name": "cortexm/branch",
        "status": "SUCCESS",
        "url": "https://ci.tlcpack.ai/job/tvm-cortexm/job/main/849/display/redirect"
      },
      {
        "name": "cpu/branch",
        "status": "SUCCESS",
        "url": "https://ci.tlcpack.ai/job/tvm-cpu/job/main/849/display/redirect"
      },
      {
        "name": "cross-isa-minimal/branch",
        "status": "SUCCESS",
        "url": "https://ci.tlcpack.ai/job/tvm-minimal-cross-isa/job/main/677/display/redirect"
      },
      {
        "name": "docker/branch",
        "status": "SUCCESS",
        "url": "https://ci.tlcpack.ai/job/tvm-docker/job/main/848/display/redirect"
      },
      {
        "name": "gpu/branch",
        "status": "SUCCESS",
        "url": "https://ci.tlcpack.ai/job/tvm-gpu/job/main/856/display/redirect"
      },
      {
        "name": "hexagon/branch",
        "status": "SUCCESS",
        "url": "https://ci.tlcpack.ai/job/tvm-hexagon/job/main/842/display/redirect"
      },
      {
        "name": "i386/branch",
        "status": "SUCCESS",
        "url": "https://ci.tlcpack.ai/job/tvm-i386/job/main/843/display/redirect"
      },
      {
        "name": "lint/branch",
        "status": "SUCCESS",
        "url": "https://ci.tlcpack.ai/job/tvm-lint/job/main/840/display/redirect"
      },
      {
        "name": "minimal/branch",
        "status": "SUCCESS",
        "url": "https://ci.tlcpack.ai/job/tvm-minimal/job/main/838/display/redirect"
      },
      {
        "name": "riscv/branch",
        "status": "SUCCESS",
        "url": "https://ci.tlcpack.ai/job/tvm-riscv/job/main/838/display/redirect"
      },
      {
        "name": "wasm/branch",
        "status": "SUCCESS",
        "url": "https://ci.tlcpack.ai/job/tvm-wasm/job/main/835/display/redirect"
      }
    ],
    "messageHeadline": "[TIR][Schedule] Derive Nonnegative Bounds from Shape Var (#15210)"
  },
  {
    "oid": "f14c61f0d177a8cf3e6e61a269c036d2b11472ba",
    "statuses": [
      {
        "name": "CI / MacOS",
        "status": "SUCCESS",
        "url": "https://github.com/apache/tvm/actions/runs/5443397616/jobs/9899869710"
      },
      {
        "name": "CI / Windows",
        "status": "SUCCESS",
        "url": "https://github.com/apache/tvm/actions/runs/5443397616/jobs/9899870191"
      },
      {
        "name": "CI / Linux-Static-Runtime",
        "status": "SUCCESS",
        "url": "https://github.com/apache/tvm/actions/runs/5443397616/jobs/9899870010"
      },
      {
        "name": "CI / Android",
        "status": "SUCCESS",
        "url": "https://github.com/apache/tvm/actions/runs/5443397616/jobs/9899869870"
      },
      {
        "name": "arm/branch",
        "status": "SUCCESS",
        "url": "https://ci.tlcpack.ai/job/tvm-arm/job/main/1145/display/redirect"
      },
      {
        "name": "cortexm/branch",
        "status": "SUCCESS",
        "url": "https://ci.tlcpack.ai/job/tvm-cortexm/job/main/848/display/redirect"
      },
      {
        "name": "cpu/branch",
        "status": "SUCCESS",
        "url": "https://ci.tlcpack.ai/job/tvm-cpu/job/main/848/display/redirect"
      },
      {
        "name": "cross-isa-minimal/branch",
        "status": "SUCCESS",
        "url": "https://ci.tlcpack.ai/job/tvm-minimal-cross-isa/job/main/676/display/redirect"
      },
      {
        "name": "docker/branch",
        "status": "SUCCESS",
        "url": "https://ci.tlcpack.ai/job/tvm-docker/job/main/847/display/redirect"
      },
      {
        "name": "gpu/branch",
        "status": "SUCCESS",
        "url": "https://ci.tlcpack.ai/job/tvm-gpu/job/main/855/display/redirect"
      },
      {
        "name": "hexagon/branch",
        "status": "SUCCESS",
        "url": "https://ci.tlcpack.ai/job/tvm-hexagon/job/main/841/display/redirect"
      },
      {
        "name": "i386/branch",
        "status": "SUCCESS",
        "url": "https://ci.tlcpack.ai/job/tvm-i386/job/main/842/display/redirect"
      },
      {
        "name": "lint/branch",
        "status": "SUCCESS",
        "url": "https://ci.tlcpack.ai/job/tvm-lint/job/main/839/display/redirect"
      },
      {
        "name": "minimal/branch",
        "status": "SUCCESS",
        "url": "https://ci.tlcpack.ai/job/tvm-minimal/job/main/837/display/redirect"
      },
      {
        "name": "riscv/branch",
        "status": "SUCCESS",
        "url": "https://ci.tlcpack.ai/job/tvm-riscv/job/main/837/display/redirect"
      },
      {
        "name": "wasm/branch",
        "status": "SUCCESS",
        "url": "https://ci.tlcpack.ai/job/tvm-wasm/job/main/834/display/redirect"
      }
    ],
    "messageHeadline": "[AOT] Remove workaround to help resolve test flakiness (#15181)"
  },
  {
    "oid": "5931cf10eb98b628ccb719e6beed7a154faa280d",
    "statuses": [
      {
        "name": "CI / MacOS",
        "status": "SUCCESS",
        "url": "https://github.com/apache/tvm/actions/runs/5440707351/jobs/9893903473"
      },
      {
        "name": "CI / Windows",
        "status": "SUCCESS",
        "url": "https://github.com/apache/tvm/actions/runs/5440707351/jobs/9893903533"
      },
      {
        "name": "CI / Linux-Static-Runtime",
        "status": "SUCCESS",
        "url": "https://github.com/apache/tvm/actions/runs/5440707351/jobs/9893903323"
      },
      {
        "name": "CI / Android",
        "status": "SUCCESS",
        "url": "https://github.com/apache/tvm/actions/runs/5440707351/jobs/9893903398"
      },
      {
        "name": "arm/branch",
        "status": "SUCCESS",
        "url": "https://ci.tlcpack.ai/job/tvm-arm/job/nightly/199/display/redirect"
      },
      {
        "name": "cortexm/branch",
        "status": "SUCCESS",
        "url": "https://ci.tlcpack.ai/job/tvm-cortexm/job/nightly/191/display/redirect"
      },
      {
        "name": "cpu/branch",
        "status": "SUCCESS",
        "url": "https://ci.tlcpack.ai/job/tvm-cpu/job/nightly/191/display/redirect"
      },
      {
        "name": "cross-isa-minimal/branch",
        "status": "SUCCESS",
        "url": "https://ci.tlcpack.ai/job/tvm-minimal-cross-isa/job/nightly/155/display/redirect"
      },
      {
        "name": "docker/branch",
        "status": "SUCCESS",
        "url": "https://ci.tlcpack.ai/job/tvm-docker/job/nightly/191/display/redirect"
      },
      {
        "name": "gpu/branch",
        "status": "SUCCESS",
        "url": "https://ci.tlcpack.ai/job/tvm-gpu/job/nightly/192/display/redirect"
      },
      {
        "name": "hexagon/branch",
        "status": "SUCCESS",
        "url": "https://ci.tlcpack.ai/job/tvm-hexagon/job/nightly/192/display/redirect"
      },
      {
        "name": "i386/branch",
        "status": "SUCCESS",
        "url": "https://ci.tlcpack.ai/job/tvm-i386/job/nightly/191/display/redirect"
      },
      {
        "name": "lint/branch",
        "status": "SUCCESS",
        "url": "https://ci.tlcpack.ai/job/tvm-lint/job/main/838/display/redirect"
      },
      {
        "name": "minimal/branch",
        "status": "SUCCESS",
        "url": "https://ci.tlcpack.ai/job/tvm-minimal/job/nightly/191/display/redirect"
      },
      {
        "name": "riscv/branch",
        "status": "SUCCESS",
        "url": "https://ci.tlcpack.ai/job/tvm-riscv/job/nightly/191/display/redirect"
      },
      {
        "name": "wasm/branch",
        "status": "SUCCESS",
        "url": "https://ci.tlcpack.ai/job/tvm-wasm/job/nightly/191/display/redirect"
      }
    ],
    "messageHeadline": "[TIR][Transform] Add LiftThreadBinding Pass (#15207)"
  },
  {
    "oid": "fb64be3f7807df18c2df6ebf5e68178e564ab0b4",
    "statuses": [
      {
        "name": "CI / MacOS",
        "status": "SUCCESS",
        "url": "https://github.com/apache/tvm/actions/runs/5440115465/jobs/9892729115"
      },
      {
        "name": "CI / Windows",
        "status": "SUCCESS",
        "url": "https://github.com/apache/tvm/actions/runs/5440115465/jobs/9892729036"
      },
      {
        "name": "CI / Linux-Static-Runtime",
        "status": "SUCCESS",
        "url": "https://github.com/apache/tvm/actions/runs/5440115465/jobs/9892728959"
      },
      {
        "name": "CI / Android",
        "status": "SUCCESS",
        "url": "https://github.com/apache/tvm/actions/runs/5440115465/jobs/9892728874"
      },
      {
        "name": "arm/branch",
        "status": "SUCCESS",
        "url": "https://ci.tlcpack.ai/job/tvm-arm/job/main/1143/display/redirect"
      },
      {
        "name": "cortexm/branch",
        "status": "SUCCESS",
        "url": "https://ci.tlcpack.ai/job/tvm-cortexm/job/main/846/display/redirect"
      },
      {
        "name": "cpu/branch",
        "status": "SUCCESS",
        "url": "https://ci.tlcpack.ai/job/tvm-cpu/job/main/846/display/redirect"
      },
      {
        "name": "cross-isa-minimal/branch",
        "status": "SUCCESS",
        "url": "https://ci.tlcpack.ai/job/tvm-minimal-cross-isa/job/main/674/display/redirect"
      },
      {
        "name": "docker/branch",
        "status": "SUCCESS",
        "url": "https://ci.tlcpack.ai/job/tvm-docker/job/main/845/display/redirect"
      },
      {
        "name": "gpu/branch",
        "status": "SUCCESS",
        "url": "https://ci.tlcpack.ai/job/tvm-gpu/job/main/853/display/redirect"
      },
      {
        "name": "hexagon/branch",
        "status": "SUCCESS",
        "url": "https://ci.tlcpack.ai/job/tvm-hexagon/job/main/839/display/redirect"
      },
      {
        "name": "i386/branch",
        "status": "SUCCESS",
        "url": "https://ci.tlcpack.ai/job/tvm-i386/job/main/840/display/redirect"
      },
      {
        "name": "lint/branch",
        "status": "SUCCESS",
        "url": "https://ci.tlcpack.ai/job/tvm-lint/job/main/837/display/redirect"
      },
      {
        "name": "minimal/branch",
        "status": "SUCCESS",
        "url": "https://ci.tlcpack.ai/job/tvm-minimal/job/main/835/display/redirect"
      },
      {
        "name": "riscv/branch",
        "status": "SUCCESS",
        "url": "https://ci.tlcpack.ai/job/tvm-riscv/job/main/835/display/redirect"
      },
      {
        "name": "wasm/branch",
        "status": "SUCCESS",
        "url": "https://ci.tlcpack.ai/job/tvm-wasm/job/main/832/display/redirect"
      }
    ],
    "messageHeadline": "[ARITH] Allow Analyzer to MarkGlobalNonNegValue (#15193)"
  },
  {
    "oid": "683dfb0c04d9f2296940e89c60c2277aca095ccd",
    "statuses": [
      {
        "name": "CI / MacOS",
        "status": "SUCCESS",
        "url": "https://github.com/apache/tvm/actions/runs/5434633678/jobs/9883195991"
      },
      {
        "name": "CI / Windows",
        "status": "SUCCESS",
        "url": "https://github.com/apache/tvm/actions/runs/5434633678/jobs/9883195924"
      },
      {
        "name": "CI / Linux-Static-Runtime",
        "status": "SUCCESS",
        "url": "https://github.com/apache/tvm/actions/runs/5434633678/jobs/9883195856"
      },
      {
        "name": "CI / Android",
        "status": "SUCCESS",
        "url": "https://github.com/apache/tvm/actions/runs/5434633678/jobs/9883196065"
      },
      {
        "name": "arm/branch",
        "status": "SUCCESS",
        "url": "https://ci.tlcpack.ai/job/tvm-arm/job/v0.13.0/1/display/redirect"
      },
      {
        "name": "cortexm/branch",
        "status": "SUCCESS",
        "url": "https://ci.tlcpack.ai/job/tvm-cortexm/job/v0.13.0/1/display/redirect"
      },
      {
        "name": "cpu/branch",
        "status": "SUCCESS",
        "url": "https://ci.tlcpack.ai/job/tvm-cpu/job/v0.13.0/1/display/redirect"
      },
      {
        "name": "cross-isa-minimal/branch",
        "status": "SUCCESS",
        "url": "https://ci.tlcpack.ai/job/tvm-minimal-cross-isa/job/v0.13.0/1/display/redirect"
      },
      {
        "name": "docker/branch",
        "status": "SUCCESS",
        "url": "https://ci.tlcpack.ai/job/tvm-docker/job/v0.13.0/1/display/redirect"
      },
      {
        "name": "gpu/branch",
        "status": "SUCCESS",
        "url": "https://ci.tlcpack.ai/job/tvm-gpu/job/v0.13.0/1/display/redirect"
      },
      {
        "name": "hexagon/branch",
        "status": "SUCCESS",
        "url": "https://ci.tlcpack.ai/job/tvm-hexagon/job/v0.13.0/1/display/redirect"
      },
      {
        "name": "i386/branch",
        "status": "SUCCESS",
        "url": "https://ci.tlcpack.ai/job/tvm-i386/job/v0.13.0/1/display/redirect"
      },
      {
        "name": "lint/branch",
        "status": "SUCCESS",
        "url": "https://ci.tlcpack.ai/job/tvm-lint/job/v0.13.0/1/display/redirect"
      },
      {
        "name": "minimal/branch",
        "status": "SUCCESS",
        "url": "https://ci.tlcpack.ai/job/tvm-minimal/job/v0.13.0/1/display/redirect"
      },
      {
        "name": "riscv/branch",
        "status": "SUCCESS",
        "url": "https://ci.tlcpack.ai/job/tvm-riscv/job/v0.13.0/1/display/redirect"
      },
      {
        "name": "wasm/branch",
        "status": "SUCCESS",
        "url": "https://ci.tlcpack.ai/job/tvm-wasm/job/v0.13.0/1/display/redirect"
      }
    ],
    "messageHeadline": "[RPC] Report RPC Session Timeout to Client Instead of \"kShutdown\" (#1\u2026"
  },
  {
    "oid": "977b4b2e05527aa8f1d48131374966e780ea8017",
    "statuses": [
      {
        "name": "CI / MacOS",
        "status": "SUCCESS",
        "url": "https://github.com/apache/tvm/actions/runs/5434289653/jobs/9882606553"
      },
      {
        "name": "CI / Windows",
        "status": "SUCCESS",
        "url": "https://github.com/apache/tvm/actions/runs/5434289653/jobs/9882606616"
      },
      {
        "name": "CI / Linux-Static-Runtime",
        "status": "SUCCESS",
        "url": "https://github.com/apache/tvm/actions/runs/5434289653/jobs/9882606490"
      },
      {
        "name": "CI / Android",
        "status": "SUCCESS",
        "url": "https://github.com/apache/tvm/actions/runs/5434289653/jobs/9882606435"
      },
      {
        "name": "arm/branch",
        "status": "SUCCESS",
        "url": "https://ci.tlcpack.ai/job/tvm-arm/job/main/1141/display/redirect"
      },
      {
        "name": "cortexm/branch",
        "status": "SUCCESS",
        "url": "https://ci.tlcpack.ai/job/tvm-cortexm/job/main/844/display/redirect"
      },
      {
        "name": "cpu/branch",
        "status": "SUCCESS",
        "url": "https://ci.tlcpack.ai/job/tvm-cpu/job/main/844/display/redirect"
      },
      {
        "name": "cross-isa-minimal/branch",
        "status": "SUCCESS",
        "url": "https://ci.tlcpack.ai/job/tvm-minimal-cross-isa/job/main/672/display/redirect"
      },
      {
        "name": "docker/branch",
        "status": "SUCCESS",
        "url": "https://ci.tlcpack.ai/job/tvm-docker/job/main/843/display/redirect"
      },
      {
        "name": "gpu/branch",
        "status": "SUCCESS",
        "url": "https://ci.tlcpack.ai/job/tvm-gpu/job/main/851/display/redirect"
      },
      {
        "name": "hexagon/branch",
        "status": "SUCCESS",
        "url": "https://ci.tlcpack.ai/job/tvm-hexagon/job/main/837/display/redirect"
      },
      {
        "name": "i386/branch",
        "status": "SUCCESS",
        "url": "https://ci.tlcpack.ai/job/tvm-i386/job/main/838/display/redirect"
      },
      {
        "name": "lint/branch",
        "status": "SUCCESS",
        "url": "https://ci.tlcpack.ai/job/tvm-lint/job/main/835/display/redirect"
      },
      {
        "name": "minimal/branch",
        "status": "SUCCESS",
        "url": "https://ci.tlcpack.ai/job/tvm-minimal/job/main/833/display/redirect"
      },
      {
        "name": "riscv/branch",
        "status": "SUCCESS",
        "url": "https://ci.tlcpack.ai/job/tvm-riscv/job/main/833/display/redirect"
      },
      {
        "name": "wasm/branch",
        "status": "SUCCESS",
        "url": "https://ci.tlcpack.ai/job/tvm-wasm/job/main/830/display/redirect"
      }
    ],
    "messageHeadline": "Update tvm_runtime.h (#15185)"
  }
]